conda_pypi/__init__.py
conda_pypi/__main__.py
conda_pypi/_version.py
conda_pypi/build.py
conda_pypi/conda_build_utils.py
conda_pypi/convert_tree.py
conda_pypi/dependencies_subprocess.py
conda_pypi/downloader.py
conda_pypi/exceptions.py
conda_pypi/grayskull_pypi_mapping.json
conda_pypi/index.py
conda_pypi/installer.py
conda_pypi/main.py
conda_pypi/paths.py
conda_pypi/plugin.py
conda_pypi/python_paths.py
conda_pypi/synth.py
conda_pypi/translate.py
conda_pypi/utils.py
conda_pypi/cli/__init__.py
conda_pypi/cli/convert.py
conda_pypi/cli/install.py
conda_pypi/cli/main.py
conda_pypi/data/EXTERNALLY-MANAGED
conda_pypi/dependencies/__init__.py
conda_pypi/dependencies/pypi.py
conda_pypi/post_command/__init__.py
conda_pypi/post_command/install.py
conda_pypi/post_command/list.py
conda_pypi-0.3.0.dist-info/METADATA
conda_pypi-0.3.0.dist-info/WHEEL
conda_pypi-0.3.0.dist-info/entry_points.txt
conda_pypi-0.3.0.dist-info/licenses/LICENSE
conda_pypi-0.3.0.dist-info/RECORD
