Metadata-Version: 2.4
Name: conda-pypi
Version: 0.3.0
Summary: Better PyPI interoperability for the conda ecosystem.
Project-URL: homepage, https://github.com/conda-incubator/conda-pypi
Author-email: Jaime Rodríguez-Guerra <jrodriguez@quansight.com>
License-Expression: MIT
License-File: LICENSE
Classifier: Programming Language :: Python :: 3
Classifier: Programming Language :: Python :: 3 :: Only
Classifier: Programming Language :: Python :: 3.9
Classifier: Programming Language :: Python :: 3.10
Classifier: Programming Language :: Python :: Implementation :: CPython
Classifier: Programming Language :: Python :: Implementation :: PyPy
Requires-Python: >=3.9
Requires-Dist: build
Requires-Dist: grayskull
Requires-Dist: installer
Requires-Dist: packaging
Requires-Dist: pip
Requires-Dist: platformdirs
Requires-Dist: pydantic
Requires-Dist: pypi-simple
Requires-Dist: requests
Requires-Dist: ruamel-yaml
Requires-Dist: typer
Requires-Dist: unearth
